{"wins": [{"id": "win_00020", "message": "Recorded patch: python", "subsystem": "patching", "created_ts": "2026-04-24T19:07:28"}, {"id": "win_00020", "message": "Recorded patch: python", "subsystem": "patching", "created_ts": "2026-04-24T19:07:28"}, {"id": "win_00020", "message": "Ran /tmp/tmponosq358.py successfully", "subsystem": "code", "created_ts": "2026-04-24T19:48:53"}, {"id": "win_00020", "message": "Ran /tmp/tmponosq358.py successfully", "subsystem": "code", "created_ts": "2026-04-24T19:48:53"}, {"id": "win_00020", "message": "Fixed /tmp/tmponosq358.py after 1 fix(es)", "subsystem": "debug", "created_ts": "2026-04-24T19:48:53"}, {"id": "win_00020", "message": "Fixed /tmp/tmponosq358.py after 1 fix(es)", "subsystem": "debug", "created_ts": "2026-04-24T19:48:53"}, {"id": "win_00020", "message": "Ran /tmp/tmp3uvvho82.py successfully", "subsystem": "code", "created_ts": "2026-04-24T19:48:54"}, {"id": "win_00020", "message": "Ran /tmp/tmp3uvvho82.py successfully", "subsystem": "code", "created_ts": "2026-04-24T19:48:54"}, {"id": "win_00020", "message": "Fixed /tmp/tmp3uvvho82.py after 1 fix(es)", "subsystem": "debug", "created_ts": "2026-04-24T19:48:54"}, {"id": "win_00020", "message": "Fixed /tmp/tmp3uvvho82.py after 1 fix(es)", "subsystem": "debug", "created_ts": "2026-04-24T19:48:54"}, {"id": "win_00020", "message": "Ran /tmp/tmpb8ixpb6o.py successfully", "subsystem": "code", "created_ts": "2026-04-24T19:48:54"}, {"id": "win_00020", "message": "Ran /tmp/tmpb8ixpb6o.py successfully", "subsystem": "code", "created_ts": "2026-04-24T19:48:54"}, {"id": "win_00020", "message": "Fixed /tmp/tmpb8ixpb6o.py after 1 fix(es)", "subsystem": "debug", "created_ts": "2026-04-24T19:48:54"}, {"id": "win_00020", "message": "Fixed /tmp/tmpb8ixpb6o.py after 1 fix(es)", "subsystem": "debug", "created_ts": "2026-04-24T19:48:54"}, {"id": "win_00020", "message": "Ran /tmp/tmpblhkv826.py successfully", "subsystem": "code", "created_ts": "2026-04-24T19:48:54"}, {"id": "win_00020", "message": "Ran /tmp/tmpblhkv826.py successfully", "subsystem": "code", "created_ts": "2026-04-24T19:48:54"}, {"id": "win_00020", "message": "Debugging /tmp/tmpblhkv826.py - no issues found", "subsystem": "debug", "created_ts": "2026-04-24T19:48:54"}, {"id": "win_00020", "message": "Debugging /tmp/tmpblhkv826.py - no issues found", "subsystem": "debug", "created_ts": "2026-04-24T19:48:54"}, {"id": "win_00020", "message": "Recorded patch: python", "subsystem": "patching", "created_ts": "2026-04-24T19:48:58"}, {"id": "win_00020", "message": "Recorded patch: python", "subsystem": "patching", "created_ts": "2026-04-24T19:48:58"}]}